[null,{"id":1,"animationId":42,"consumable":true,"damage":{"critical":false,"elementId":0,"formula":"0","type":0,"variance":20},"description":"治疗被注入了治愈的力量的贵重的灵札裂伤和幻惑，全部恢复体力和\n灵力的最大持有数3","effects":[{"code":11,"dataId":0,"value1":1,"value2":0},{"code":12,"dataId":0,"value1":1,"value2":0},{"code":22,"dataId":4,"value1":1,"value2":0},{"code":22,"dataId":5,"value1":1,"value2":0}],"hitType":0,"iconIndex":188,"itypeId":1,"name":"治愈的灵符","note":"itemMaxNum:3\n<picture-action: hu_kaihuku>\n<voice-action: kaihuku>","occasion":0,"price":1000,"repeats":1,"scope":11,"speed":999,"successRate":100,"tpGain":0},{"id":2,"animationId":0,"consumable":false,"damage":{"critical":false,"elementId":0,"formula":"0","type":0,"variance":20},"description":"能够强化强化强化使用者灵力的贵重的灵牌斩妖刀或装灵具","effects":[{"code":44,"dataId":1,"value1":1,"value2":0}],"hitType":0,"iconIndex":188,"itypeId":1,"name":"强化的灵符","note":"","occasion":2,"price":2000,"repeats":1,"scope":0,"speed":0,"successRate":100,"tpGain":0},{"id":3,"animationId":41,"consumable":true,"damage":{"critical":false,"elementId":0,"formula":"0","type":0,"variance":20},"description":"隐藏魂魄结晶化的治愈力量的灵药体力稍微恢复的最大持有数10","effects":[{"code":11,"dataId":0,"value1":0.1,"value2":35}],"hitType":0,"iconIndex":208,"itypeId":1,"name":"魂魄丸","note":"itemMaxNum:10\n<picture-action: hu_kaihuku>\n<voice-action: kaihuku>","occasion":0,"price":12,"repeats":1,"scope":11,"speed":0,"successRate":100,"tpGain":0},{"id":4,"animationId":46,"consumable":true,"damage":{"critical":false,"elementId":0,"formula":"0","type":0,"variance":20},"description":"能稍微恢复凝缩了灵力的苍白发光的宝玉灵力的最大持有数10","effects":[{"code":12,"dataId":0,"value1":0.1,"value2":40}],"hitType":0,"iconIndex":196,"itypeId":1,"name":"灵气弹","note":"itemMaxNum:10\n<picture-action: hu_kaihuku>\n<voice-action: kaihuku>","occasion":0,"price":100,"repeats":1,"scope":11,"speed":0,"successRate":100,"tpGain":0},{"id":5,"animationId":45,"consumable":true,"damage":{"critical":false,"elementId":0,"formula":"0","type":0,"variance":20},"description":"治疗母乳体质妖魔寄生灵敏度上升的秘药最大持有数15","effects":[{"code":22,"dataId":7,"value1":1,"value2":0},{"code":22,"dataId":9,"value1":1,"value2":0},{"code":22,"dataId":17,"value1":1,"value2":0}],"hitType":0,"iconIndex":228,"itypeId":1,"name":"净化药","note":"itemMaxNum:15\n<picture-action: hu_kaihuku>\n<voice-action: kaihuku>","occasion":0,"price":8,"repeats":1,"scope":11,"speed":0,"successRate":100,"tpGain":0},{"id":6,"animationId":40,"consumable":true,"damage":{"critical":false,"elementId":0,"formula":"0","type":0,"variance":20},"description":"使理智疯狂夺取判断力的魔之秘石敌人全体成为混乱状态的最大持有\n数2","effects":[{"code":21,"dataId":14,"value1":1,"value2":0}],"hitType":2,"iconIndex":302,"itypeId":1,"name":"月亮的碎片","note":"itemMaxNum:2\n<picture-action: hu_kougeki>\n<voice-action: attackitem>","occasion":1,"price":40,"repeats":1,"scope":2,"speed":0,"successRate":100,"tpGain":0},{"id":7,"animationId":35,"consumable":true,"damage":{"critical":false,"elementId":0,"formula":"0","type":0,"variance":20},"description":"喷出迷惑对方的幻惑之烟的玉敌全体幻惑状态的最大持有数2","effects":[{"code":21,"dataId":5,"value1":1,"value2":0}],"hitType":2,"iconIndex":299,"itypeId":1,"name":"迷幻的烟珠","note":"itemMaxNum:2\n<picture-action: hu_kougeki>\n<voice-action: attackitem>","occasion":1,"price":28,"repeats":1,"scope":2,"speed":0,"successRate":100,"tpGain":0},{"id":8,"animationId":0,"consumable":false,"damage":{"critical":false,"elementId":0,"formula":"0","type":0,"variance":20},"description":"带着又粗又硬的振动功能的大人的玩具淫乱Lv 2以上的时候在自\n己家使用的话…？","effects":[{"code":44,"dataId":39,"value1":1,"value2":0},{"code":21,"dataId":19,"value1":1,"value2":0},{"code":22,"dataId":19,"value1":1,"value2":0}],"hitType":0,"iconIndex":84,"itypeId":1,"name":"按摩棒","note":"<picture-action: onabai>\n\n\n","occasion":3,"price":100,"repeats":4,"scope":11,"speed":0,"successRate":100,"tpGain":0},{"id":9,"animationId":0,"consumable":false,"damage":{"critical":false,"elementId":0,"formula":"0","type":0,"variance":20},"description":"适合责备乳头的大人的玩具淫乱Lv 2以上的时候在自己家使用的\n话…？","effects":[{"code":44,"dataId":40,"value1":1,"value2":0},{"code":21,"dataId":19,"value1":1,"value2":0},{"code":22,"dataId":19,"value1":1,"value2":0}],"hitType":0,"iconIndex":84,"itypeId":1,"name":"电刷转子","note":"<picture-action: onaburasi>\n\n\n","occasion":3,"price":100,"repeats":4,"scope":11,"speed":0,"successRate":100,"tpGain":0},{"id":10,"animationId":0,"consumable":false,"damage":{"critical":false,"elementId":0,"formula":"0","type":0,"variance":20},"description":"转移到内衣的淫乱邪神被封印了的纸币淫乱Lv 3以上的时候在自\n己家使用的话…？","effects":[{"code":44,"dataId":41,"value1":1,"value2":0},{"code":22,"dataId":19,"value1":1,"value2":0}],"hitType":0,"iconIndex":84,"itypeId":1,"name":"付丧神的淫札","note":"<picture-action: onasyoku>\n\n\n","occasion":3,"price":500,"repeats":4,"scope":11,"speed":0,"successRate":100,"tpGain":0},{"id":11,"animationId":0,"consumable":true,"damage":{"critical":false,"elementId":0,"formula":"0","type":0,"variance":20},"description":"读了各种可疑内容的面向大人的书，淫乱度上升了5","effects":[{"code":21,"dataId":19,"value1":1,"value2":0},{"code":22,"dataId":19,"value1":1,"value2":0},{"code":44,"dataId":38,"value1":1,"value2":0}],"hitType":0,"iconIndex":84,"itypeId":1,"name":"黄色的书","note":"","occasion":0,"price":300,"repeats":1,"scope":7,"speed":0,"successRate":100,"tpGain":0},{"id":12,"animationId":0,"consumable":true,"damage":{"critical":false,"elementId":0,"formula":"0","type":0,"variance":20},"description":"开放被隐藏的雌的本能的强烈的春药淫乱度和快乐度+50灵敏度上\n升了","effects":[{"code":44,"dataId":236,"value1":1,"value2":0},{"code":21,"dataId":17,"value1":1,"value2":0}],"hitType":0,"iconIndex":179,"itypeId":1,"name":"春药","note":"<voice-action: hatujo>","occasion":0,"price":150,"repeats":1,"scope":7,"speed":0,"successRate":100,"tpGain":0},{"id":13,"animationId":0,"consumable":true,"damage":{"critical":false,"elementId":0,"formula":"0","type":0,"variance":20},"description":"安定精神抑制性欲的药淫乱度和快乐度为0治疗灵敏度上升","effects":[{"code":22,"dataId":17,"value1":1,"value2":0},{"code":44,"dataId":235,"value1":1,"value2":0}],"hitType":0,"iconIndex":180,"itypeId":1,"name":"抑情灵药","note":"<voice-action: kaihuku>","occasion":0,"price":20,"repeats":1,"scope":7,"speed":0,"successRate":100,"tpGain":0},{"id":14,"animationId":0,"consumable":true,"damage":{"critical":false,"elementId":0,"formula":"0","type":0,"variance":20},"description":"妖魔分泌的促进母乳分泌的妖魔鬼怪的液体喝了就会变成“母乳体质","effects":[{"code":21,"dataId":7,"value1":1,"value2":0}],"hitType":0,"iconIndex":84,"itypeId":1,"name":"妖魔的体液","note":"<voice-action: taieki>","occasion":0,"price":400,"repeats":1,"scope":11,"speed":0,"successRate":100,"tpGain":0},{"id":15,"animationId":0,"consumable":true,"damage":{"critical":false,"elementId":0,"formula":"0","type":0,"variance":20},"description":"使用寄生在胎内吸收宿主灵力的妖魔之卵就会变成“妖魔寄生","effects":[{"code":21,"dataId":9,"value1":1,"value2":0}],"hitType":0,"iconIndex":84,"itypeId":1,"name":"妖魔之卵","note":"<voice-action: maran>","occasion":0,"price":400,"repeats":1,"scope":11,"speed":0,"successRate":100,"tpGain":0},{"id":16,"animationId":0,"consumable":false,"damage":{"critical":false,"elementId":0,"formula":"0","type":0,"variance":20},"description":"在写着几乎所有人都想要的10000张纸片的哦店可以和魂魄交换","effects":[],"hitType":0,"iconIndex":188,"itypeId":1,"name":"谕吉的纸","note":"","occasion":3,"price":200,"repeats":1,"scope":0,"speed":0,"successRate":100,"tpGain":0},{"id":17,"animationId":0,"consumable":true,"damage":{"critical":false,"elementId":0,"formula":"0","type":0,"variance":20},"description":"熟读记载着退魔师战术的珍贵卷轴，的话，作为退魔师的水平会上升","effects":[{"code":44,"dataId":7,"value1":1,"value2":0}],"hitType":0,"iconIndex":191,"itypeId":1,"name":"秘传的卷物","note":"","occasion":2,"price":2000,"repeats":1,"scope":11,"speed":0,"successRate":100,"tpGain":0},{"id":18,"animationId":0,"consumable":true,"damage":{"critical":false,"elementId":0,"formula":"0","type":0,"variance":20},"description":"嘴里充满力量的不可思议的丸药真利的攻击力稍微上升","effects":[{"code":42,"dataId":2,"value1":3,"value2":0}],"hitType":0,"iconIndex":208,"itypeId":1,"name":"力量药丸","note":"","occasion":2,"price":500,"repeats":1,"scope":11,"speed":0,"successRate":100,"tpGain":0},{"id":19,"animationId":0,"consumable":true,"damage":{"critical":false,"elementId":0,"formula":"0","type":0,"variance":20},"description":"口中所说的得到丰富的巫力的不可思议的丸药真利的巫力稍微上升","effects":[{"code":42,"dataId":4,"value1":3,"value2":0}],"hitType":0,"iconIndex":208,"itypeId":1,"name":"巫力药丸","note":"","occasion":2,"price":500,"repeats":1,"scope":11,"speed":0,"successRate":100,"tpGain":0},{"id":20,"animationId":0,"consumable":true,"damage":{"critical":false,"elementId":0,"formula":"0","type":0,"variance":20},"description":"给吃的人带来敏捷的不可思议的丸药真利的速度稍微上升","effects":[{"code":42,"dataId":6,"value1":2,"value2":0}],"hitType":0,"iconIndex":208,"itypeId":1,"name":"快速药丸","note":"","occasion":2,"price":500,"repeats":1,"scope":11,"speed":0,"successRate":100,"tpGain":0},{"id":21,"animationId":0,"consumable":true,"damage":{"critical":false,"elementId":0,"formula":"0","type":0,"variance":20},"description":"增加从敌人的攻击中保护自己的力量不可思议的丸药真利的防御力稍\n微上升","effects":[{"code":42,"dataId":3,"value1":4,"value2":0}],"hitType":0,"iconIndex":208,"itypeId":1,"name":"守护药丸","note":"","occasion":2,"price":500,"repeats":1,"scope":11,"speed":0,"successRate":100,"tpGain":0},{"id":22,"animationId":0,"consumable":true,"damage":{"critical":false,"elementId":0,"formula":"0","type":0,"variance":20},"description":"含有丰富生命力的神奇药丸真利的最大体力稍微上升","effects":[{"code":42,"dataId":0,"value1":5,"value2":0}],"hitType":0,"iconIndex":208,"itypeId":1,"name":"生命药丸","note":"","occasion":2,"price":500,"repeats":1,"scope":11,"speed":0,"successRate":100,"tpGain":0},{"id":23,"animationId":0,"consumable":true,"damage":{"critical":false,"elementId":0,"formula":"0","type":0,"variance":20},"description":"口中所藏的释放灵力的不可思议的丸药真利的最大灵力稍微上升","effects":[{"code":42,"dataId":1,"value1":5,"value2":0}],"hitType":0,"iconIndex":208,"itypeId":1,"name":"灵力药丸","note":"","occasion":2,"price":500,"repeats":1,"scope":11,"speed":0,"successRate":100,"tpGain":0},{"id":24,"animationId":0,"consumable":true,"damage":{"critical":false,"elementId":0,"formula":"0","type":0,"variance":20},"description":"能消除自己的气息的妖鸟的羽毛妖魔被注意到，不就能回到安全的地\n方","effects":[{"code":44,"dataId":19,"value1":1,"value2":0}],"hitType":0,"iconIndex":225,"itypeId":1,"name":"漆黑的羽毛","note":"","occasion":2,"price":25,"repeats":1,"scope":0,"speed":0,"successRate":100,"tpGain":0}]